BIA/__init__.py
BIA/main.py
BIA/static/__init__.py
BIA/static/dist/css/output.css
BIA/static/dist/node_modules/.package-lock.json
BIA/static/dist/node_modules/.bin/acorn
BIA/static/dist/node_modules/.bin/acorn.cmd
BIA/static/dist/node_modules/.bin/acorn.ps1
BIA/static/dist/node_modules/.bin/cssesc
BIA/static/dist/node_modules/.bin/cssesc.cmd
BIA/static/dist/node_modules/.bin/cssesc.ps1
BIA/static/dist/node_modules/.bin/detective
BIA/static/dist/node_modules/.bin/detective.cmd
BIA/static/dist/node_modules/.bin/detective.ps1
BIA/static/dist/node_modules/.bin/mini-svg-data-uri
BIA/static/dist/node_modules/.bin/mini-svg-data-uri.cmd
BIA/static/dist/node_modules/.bin/mini-svg-data-uri.ps1
BIA/static/dist/node_modules/.bin/nanoid
BIA/static/dist/node_modules/.bin/nanoid.cmd
BIA/static/dist/node_modules/.bin/nanoid.ps1
BIA/static/dist/node_modules/.bin/resolve
BIA/static/dist/node_modules/.bin/resolve.cmd
BIA/static/dist/node_modules/.bin/resolve.ps1
BIA/static/dist/node_modules/.bin/tailwind
BIA/static/dist/node_modules/.bin/tailwind.cmd
BIA/static/dist/node_modules/.bin/tailwind.ps1
BIA/static/dist/node_modules/.bin/tailwindcss
BIA/static/dist/node_modules/.bin/tailwindcss.cmd
BIA/static/dist/node_modules/.bin/tailwindcss.ps1
BIA/static/dist/node_modules/@nodelib/fs.scandir/LICENSE
BIA/static/dist/node_modules/@nodelib/fs.scandir/README.md
BIA/static/dist/node_modules/@nodelib/fs.scandir/package.json
BIA/static/dist/node_modules/@nodelib/fs.scandir/out/constants.d.ts
BIA/static/dist/node_modules/@nodelib/fs.scandir/out/constants.js
BIA/static/dist/node_modules/@nodelib/fs.scandir/out/index.d.ts
BIA/static/dist/node_modules/@nodelib/fs.scandir/out/index.js
BIA/static/dist/node_modules/@nodelib/fs.scandir/out/settings.d.ts
BIA/static/dist/node_modules/@nodelib/fs.scandir/out/settings.js
BIA/static/dist/node_modules/@nodelib/fs.scandir/out/adapters/fs.d.ts
BIA/static/dist/node_modules/@nodelib/fs.scandir/out/adapters/fs.js
BIA_OBS-1.0.3.dist-info/METADATA
BIA_OBS-1.0.3.dist-info/WHEEL
BIA_OBS-1.0.3.dist-info/top_level.txt
BIA_OBS-1.0.3.dist-info/RECORD
